{
    "@context": [
        "http://www.w3.org/ns/td",
        {
            "sdf": "https://example.com/sdf"
        }
    ],
    "@type": "tm:ThingModel",
    "title": "Humidity",
    "description": "copyright 2016-2017, 2019 Open Connectivity Foundation, Inc. All rights reserved.",
    "links": [
        {
            "href": "https://github.com/one-data-model/oneDM/blob/master/LICENSE",
            "rel": "license"
        }
    ],
    "version": {
        "instance": "2019-02-15"
    },
    "tm:required": [
        "#/properties/humidity_desiredHumidity"
    ],
    "properties": {
        "humidity_desiredHumidity": {
            "sdf:jsonPointer": "#/sdfObject/humidity/sdfProperty/desiredHumidity",
            "description": "The desired value for humidity.",
            "type": "integer",
            "minimum": 0,
            "maximum": 100
        },
        "humidity_humidity": {
            "sdf:jsonPointer": "#/sdfObject/humidity/sdfProperty/humidity",
            "description": "The current sensed value for humidity.",
            "readOnly": true,
            "type": "integer",
            "minimum": 0,
            "maximum": 100
        }
    }
}